LICENSE.txt
README.md
setup.cfg
setup.py
Topsis_Sukhmanpreet_102053028/102053028.py
Topsis_Sukhmanpreet_102053028/__init__.py
Topsis_Sukhmanpreet_102053028.egg-info/PKG-INFO
Topsis_Sukhmanpreet_102053028.egg-info/SOURCES.txt
Topsis_Sukhmanpreet_102053028.egg-info/dependency_links.txt
Topsis_Sukhmanpreet_102053028.egg-info/requires.txt
Topsis_Sukhmanpreet_102053028.egg-info/top_level.txt