Metadata-Version: 2.1
Name: Topsis-Sukhmanpreet-102053028
Version: 0.1
Summary: This package is implimentation of multi-criteria decision analysis using topsis
Author: Charu Bansal
License: MIT
Keywords: topsis
Classifier: Development Status :: 3 - Alpha
Classifier: Intended Audience :: Developers
Classifier: Topic :: Software Development :: Build Tools
Classifier: License :: OSI Approved :: MIT License
Classifier: Programming Language :: Python :: 3
Classifier: Programming Language :: Python :: 3.4
Classifier: Programming Language :: Python :: 3.5
Classifier: Programming Language :: Python :: 3.6
License-File: LICENSE.txt
